{
   "table-count" : 1,
   "warnings" : [],
   "error-count" : 3,
   "tables" : [
      {
         "schema" : null,
         "time" : 0.032,
         "source" : "data/awful.csv",
         "encoding" : "utf-8",
         "scheme" : "file",
         "errors" : [
            {
+              "processor": "csvlint",
               "code" : "duplicate-header",
               "row-number" : null,
               "message" : "Header in column 4 is duplicated to header in column(s) 2",
               "row" : null,
               "column-number" : 4
            },
            {
+              "processor": "goodtables",
               "row" : [
                  "4",
                  "Salad",
                  "3"
               ],
               "message" : "Row 5 has a missing value in column 4",
               "column-number" : 4,
               "code" : "missing-value",
               "row-number" : 5
            },
            {
+              "processor": "goodtables",
               "column-number" : 5,
               "message" : "Row 5 has a missing value in column 5",
               "row" : [
                  "4",
                  "Salad",
                  "3"
               ],
               "row-number" : 5,
               "code" : "missing-value"
            }
         ],
         "format" : "csv",
         "row-count" : 5,
         "valid" : false,
         "headers" : [
            "ID",
            "Mean",
            "N",
            "Mean",
            "Standard Deviation"
         ],
         "error-count" : 3
      }
   ],
   "preset" : "table",
   "valid" : false,
   "time" : 0.035
}
